ozon3/__init__.py
ozon3/ozon3.py
ozon3/urls.py
ozon3/historical/__init__.py
ozon3/historical/_reverse_engineered.py
ozon3/historical/relevant_funcs.py
ozon3-4.0.2.dist-info/LICENSE
ozon3-4.0.2.dist-info/METADATA
ozon3-4.0.2.dist-info/WHEEL
ozon3-4.0.2.dist-info/top_level.txt
ozon3-4.0.2.dist-info/RECORD
