Metadata-Version: 2.1
Name: ozon3
Version: 4.0.2
Summary: An open-source package to easily obtain real-time, historical,or forecasted air quality data for anywhere in the world. Reliable,accurate and simple.
Home-page: https://github.com/Ozon3Org/Ozon3
Download-URL: https://github.com/Ozon3Org/Ozon3/archive/refs/tags/v4.0.2.tar.gz
Author: Milind Sharma
Author-email: milindsharma8@gmail.com
License: GPLv3+
Keywords: aqi,air quality,world air quality,api,open source
Classifier: Development Status :: 5 - Production/Stable
Classifier: Intended Audience :: Developers
Classifier: Topic :: Software Development :: Build Tools
Classifier: License :: OSI Approved :: GNU General Public License v3 or later (GPLv3+)
Classifier: Programming Language :: Python :: 3.6
Classifier: Programming Language :: Python :: 3.7
Classifier: Programming Language :: Python :: 3.8
Classifier: Programming Language :: Python :: 3.9
Requires-Python: >=3.6
License-File: LICENSE
